HtmlCanvasDeepDive/README.md
HtmlCanvasDeepDive/__init__.py
HtmlCanvasDeepDive/__main__.py
HtmlCanvasDeepDive/file.epub
HtmlCanvasDeepDive/index.html
HtmlCanvasDeepDive/css/__init__.py
HtmlCanvasDeepDive/css/annotations.css
HtmlCanvasDeepDive/css/main.css
HtmlCanvasDeepDive/css/normalize.css
HtmlCanvasDeepDive/css/popup.css
HtmlCanvasDeepDive/font/__init__.py
HtmlCanvasDeepDive/font/fontello.eot
HtmlCanvasDeepDive/font/fontello.svg
HtmlCanvasDeepDive/font/fontello.ttf
HtmlCanvasDeepDive/font/fontello.woff
HtmlCanvasDeepDive/img/__init__.py
HtmlCanvasDeepDive/img/annotator-glyph-sprite.png
HtmlCanvasDeepDive/img/annotator-icon-sprite.png
HtmlCanvasDeepDive/img/apple-touch-icon.png
HtmlCanvasDeepDive/img/cancelfullscreen.png
HtmlCanvasDeepDive/img/close.png
HtmlCanvasDeepDive/img/fullscreen.png
HtmlCanvasDeepDive/img/loader.gif
HtmlCanvasDeepDive/img/menu-icon.png
HtmlCanvasDeepDive/img/save.png
HtmlCanvasDeepDive/img/saved.png
HtmlCanvasDeepDive/img/settings-s.png
HtmlCanvasDeepDive/img/settings.png
HtmlCanvasDeepDive/img/star.png
HtmlCanvasDeepDive/js/__init__.py
HtmlCanvasDeepDive/js/epub.js
HtmlCanvasDeepDive/js/epub.min.js
HtmlCanvasDeepDive/js/epub.min.map
HtmlCanvasDeepDive/js/hooks.min.js
HtmlCanvasDeepDive/js/hooks.min.map
HtmlCanvasDeepDive/js/reader.js
HtmlCanvasDeepDive/js/reader.js.map
HtmlCanvasDeepDive/js/reader.min.js
HtmlCanvasDeepDive/js/reader.min.map
HtmlCanvasDeepDive/js/hooks/__init__.py
HtmlCanvasDeepDive/js/hooks/extensions/__init__.py
HtmlCanvasDeepDive/js/hooks/extensions/highlight.js
HtmlCanvasDeepDive/js/libs/__init__.py
HtmlCanvasDeepDive/js/libs/jquery.min.js
HtmlCanvasDeepDive/js/libs/localforage.min.js
HtmlCanvasDeepDive/js/libs/screenfull.js
HtmlCanvasDeepDive/js/libs/screenfull.min.js
HtmlCanvasDeepDive/js/libs/zip.min.js
HtmlCanvasDeepDive/js/plugins/__init__.py
HtmlCanvasDeepDive/js/plugins/hypothesis.js
HtmlCanvasDeepDive/js/plugins/search.js
html_canvas_deep_dive-2024.3.2.0.dist-info/METADATA
html_canvas_deep_dive-2024.3.2.0.dist-info/WHEEL
html_canvas_deep_dive-2024.3.2.0.dist-info/entry_points.txt
html_canvas_deep_dive-2024.3.2.0.dist-info/top_level.txt
html_canvas_deep_dive-2024.3.2.0.dist-info/RECORD
